env_exec/__about__.py
env_exec/__init__.py
env_exec/errors.py
env_exec/cli/__init__.py
env_exec/cli/cli.py
env_exec/environments/__init__.py
env_exec/environments/conda.py
env_exec/environments/env.py
env_exec/environments/mamba.py
env_exec-1.6.0.dist-info/METADATA
env_exec-1.6.0.dist-info/WHEEL
env_exec-1.6.0.dist-info/entry_points.txt
env_exec-1.6.0.dist-info/licenses/LICENSE.txt
env_exec-1.6.0.dist-info/RECORD
