Metadata-Version: 2.1
Name: env-exec
Version: 1.6.0
Summary: Programmatically execute commands in environments.
Project-URL: Documentation, https://github.com/unknown/env-exec#readme
Project-URL: Issues, https://github.com/unknown/env-exec/issues
Project-URL: Source, https://github.com/unknown/env-exec
Author-email: Wytamma Wirth <wytamma.wirth@me.com>
License-Expression: MIT
License-File: LICENSE.txt
Classifier: Development Status :: 4 - Beta
Classifier: Programming Language :: Python
Classifier: Programming Language :: Python :: 3.7
Classifier: Programming Language :: Python :: 3.8
Classifier: Programming Language :: Python :: 3.9
Classifier: Programming Language :: Python :: 3.10
Classifier: Programming Language :: Python :: 3.11
Classifier: Programming Language :: Python :: Implementation :: CPython
Classifier: Programming Language :: Python :: Implementation :: PyPy
Requires-Python: >=3.7
